{
  "service": "forecast",
  "csp": "aws",
  "generated_at": "2026-02-20T16:03:41.421112+00:00",
  "total_operations": 33,
  "independent_count": 0,
  "dependent_count": 33,
  "operations": {
    "CreateAutoPredictor": {
      "operation": "CreateAutoPredictor",
      "service": "forecast",
      "csp": "aws",
      "independent": false,
      "python_method": "create_auto_predictor",
      "yaml_action": "create_auto_predictor",
      "required_params": [
        "PredictorName"
      ],
      "optional_params": [
        "ForecastHorizon",
        "ForecastTypes",
        "ForecastDimensions",
        "ForecastFrequency",
        "DataConfig",
        "EncryptionConfig",
        "ReferencePredictorArn",
        "OptimizationMetric",
        "ExplainPredictor",
        "Tags",
        "MonitorConfig",
        "TimeAlignmentBoundary"
      ],
      "output_fields": {
        "PredictorArn": {
          "type": "string",
          "description": "<p>The Amazon Resource Name (ARN) of the predictor.</p>",
          "enum": false,
          "operators": [
            "equals",
            "not_equals",
            "contains",
            "in",
            "exists"
          ],
          "compliance_category": "identity"
        }
      },
      "kind": "write_create"
    },
    "CreateDataset": {
      "operation": "CreateDataset",
      "service": "forecast",
      "csp": "aws",
      "independent": false,
      "python_method": "create_dataset",
      "yaml_action": "create_dataset",
      "required_params": [
        "DatasetName",
        "Domain",
        "DatasetType",
        "Schema"
      ],
      "optional_params": [
        "DataFrequency",
        "EncryptionConfig",
        "Tags"
      ],
      "output_fields": {
        "DatasetArn": {
          "type": "string",
          "description": "<p>The Amazon Resource Name (ARN) of the dataset.</p>",
          "enum": false,
          "operators": [
            "equals",
            "not_equals",
            "contains",
            "in",
            "exists"
          ],
          "compliance_category": "identity"
        }
      },
      "kind": "write_create"
    },
    "CreateDatasetGroup": {
      "operation": "CreateDatasetGroup",
      "service": "forecast",
      "csp": "aws",
      "independent": false,
      "python_method": "create_dataset_group",
      "yaml_action": "create_dataset_group",
      "required_params": [
        "DatasetGroupName",
        "Domain"
      ],
      "optional_params": [
        "DatasetArns",
        "Tags"
      ],
      "output_fields": {
        "DatasetGroupArn": {
          "type": "string",
          "description": "<p>The Amazon Resource Name (ARN) of the dataset group.</p>",
          "enum": false,
          "operators": [
            "equals",
            "not_equals",
            "contains",
            "in",
            "exists"
          ],
          "compliance_category": "identity"
        }
      },
      "kind": "write_create"
    },
    "CreateDatasetImportJob": {
      "operation": "CreateDatasetImportJob",
      "service": "forecast",
      "csp": "aws",
      "independent": false,
      "python_method": "create_dataset_import_job",
      "yaml_action": "create_dataset_import_job",
      "required_params": [
        "DatasetImportJobName",
        "DatasetArn",
        "DataSource"
      ],
      "optional_params": [
        "TimestampFormat",
        "TimeZone",
        "UseGeolocationForTimeZone",
        "GeolocationFormat",
        "Tags",
        "Format",
        "ImportMode"
      ],
      "output_fields": {
        "DatasetImportJobArn": {
          "type": "string",
          "description": "<p>The Amazon Resource Name (ARN) of the dataset import job.</p>",
          "enum": false,
          "operators": [
            "equals",
            "not_equals",
            "contains",
            "in",
            "exists"
          ],
          "compliance_category": "identity"
        }
      },
      "kind": "write_create"
    },
    "CreateExplainability": {
      "operation": "CreateExplainability",
      "service": "forecast",
      "csp": "aws",
      "independent": false,
      "python_method": "create_explainability",
      "yaml_action": "create_explainability",
      "required_params": [
        "ExplainabilityName",
        "ResourceArn",
        "ExplainabilityConfig"
      ],
      "optional_params": [
        "DataSource",
        "Schema",
        "EnableVisualization",
        "StartDateTime",
        "EndDateTime",
        "Tags"
      ],
      "output_fields": {
        "ExplainabilityArn": {
          "type": "string",
          "description": "<p>The Amazon Resource Name (ARN) of the Explainability.</p>",
          "enum": false,
          "operators": [
            "equals",
            "not_equals",
            "contains",
            "in",
            "exists"
          ],
          "compliance_category": "identity"
        }
      },
      "kind": "write_create"
    },
    "CreateExplainabilityExport": {
      "operation": "CreateExplainabilityExport",
      "service": "forecast",
      "csp": "aws",
      "independent": false,
      "python_method": "create_explainability_export",
      "yaml_action": "create_explainability_export",
      "required_params": [
        "ExplainabilityExportName",
        "ExplainabilityArn",
        "Destination"
      ],
      "optional_params": [
        "Tags",
        "Format"
      ],
      "output_fields": {
        "ExplainabilityExportArn": {
          "type": "string",
          "description": "<p>The Amazon Resource Name (ARN) of the export.</p>",
          "enum": false,
          "operators": [
            "equals",
            "not_equals",
            "contains",
            "in",
            "exists"
          ],
          "compliance_category": "identity"
        }
      },
      "kind": "write_create"
    },
    "CreateForecast": {
      "operation": "CreateForecast",
      "service": "forecast",
      "csp": "aws",
      "independent": false,
      "python_method": "create_forecast",
      "yaml_action": "create_forecast",
      "required_params": [
        "ForecastName",
        "PredictorArn"
      ],
      "optional_params": [
        "ForecastTypes",
        "Tags",
        "TimeSeriesSelector"
      ],
      "output_fields": {
        "ForecastArn": {
          "type": "string",
          "description": "<p>The Amazon Resource Name (ARN) of the forecast.</p>",
          "enum": false,
          "operators": [
            "equals",
            "not_equals",
            "contains",
            "in",
            "exists"
          ],
          "compliance_category": "identity"
        }
      },
      "kind": "write_create"
    },
    "CreateForecastExportJob": {
      "operation": "CreateForecastExportJob",
      "service": "forecast",
      "csp": "aws",
      "independent": false,
      "python_method": "create_forecast_export_job",
      "yaml_action": "create_forecast_export_job",
      "required_params": [
        "ForecastExportJobName",
        "ForecastArn",
        "Destination"
      ],
      "optional_params": [
        "Tags",
        "Format"
      ],
      "output_fields": {
        "ForecastExportJobArn": {
          "type": "string",
          "description": "<p>The Amazon Resource Name (ARN) of the export job.</p>",
          "enum": false,
          "operators": [
            "equals",
            "not_equals",
            "contains",
            "in",
            "exists"
          ],
          "compliance_category": "identity"
        }
      },
      "kind": "write_create"
    },
    "CreateMonitor": {
      "operation": "CreateMonitor",
      "service": "forecast",
      "csp": "aws",
      "independent": false,
      "python_method": "create_monitor",
      "yaml_action": "create_monitor",
      "required_params": [
        "MonitorName",
        "ResourceArn"
      ],
      "optional_params": [
        "Tags"
      ],
      "output_fields": {
        "MonitorArn": {
          "type": "string",
          "description": "<p>The Amazon Resource Name (ARN) of the monitor resource.</p>",
          "enum": false,
          "operators": [
            "equals",
            "not_equals",
            "contains",
            "in",
            "exists"
          ],
          "compliance_category": "identity"
        }
      },
      "kind": "write_create"
    },
    "CreatePredictor": {
      "operation": "CreatePredictor",
      "service": "forecast",
      "csp": "aws",
      "independent": false,
      "python_method": "create_predictor",
      "yaml_action": "create_predictor",
      "required_params": [
        "PredictorName",
        "ForecastHorizon",
        "InputDataConfig",
        "FeaturizationConfig"
      ],
      "optional_params": [
        "AlgorithmArn",
        "ForecastTypes",
        "PerformAutoML",
        "AutoMLOverrideStrategy",
        "PerformHPO",
        "TrainingParameters",
        "EvaluationParameters",
        "HPOConfig",
        "EncryptionConfig",
        "Tags",
        "OptimizationMetric"
      ],
      "output_fields": {
        "PredictorArn": {
          "type": "string",
          "description": "<p>The Amazon Resource Name (ARN) of the predictor.</p>",
          "enum": false,
          "operators": [
            "equals",
            "not_equals",
            "contains",
            "in",
            "exists"
          ],
          "compliance_category": "identity"
        }
      },
      "kind": "write_create"
    },
    "CreatePredictorBacktestExportJob": {
      "operation": "CreatePredictorBacktestExportJob",
      "service": "forecast",
      "csp": "aws",
      "independent": false,
      "python_method": "create_predictor_backtest_export_job",
      "yaml_action": "create_predictor_backtest_export_job",
      "required_params": [
        "PredictorBacktestExportJobName",
        "PredictorArn",
        "Destination"
      ],
      "optional_params": [
        "Tags",
        "Format"
      ],
      "output_fields": {
        "PredictorBacktestExportJobArn": {
          "type": "string",
          "description": "<p>The Amazon Resource Name (ARN) of the predictor backtest export job that you want to export.</p>",
          "enum": false,
          "operators": [
            "equals",
            "not_equals",
            "contains",
            "in",
            "exists"
          ],
          "compliance_category": "identity"
        }
      },
      "kind": "write_create"
    },
    "CreateWhatIfAnalysis": {
      "operation": "CreateWhatIfAnalysis",
      "service": "forecast",
      "csp": "aws",
      "independent": false,
      "python_method": "create_what_if_analysis",
      "yaml_action": "create_what_if_analysis",
      "required_params": [
        "WhatIfAnalysisName",
        "ForecastArn"
      ],
      "optional_params": [
        "TimeSeriesSelector",
        "Tags"
      ],
      "output_fields": {
        "WhatIfAnalysisArn": {
          "type": "string",
          "description": "<p>The Amazon Resource Name (ARN) of the what-if analysis.</p>",
          "enum": false,
          "operators": [
            "equals",
            "not_equals",
            "contains",
            "in",
            "exists"
          ],
          "compliance_category": "identity"
        }
      },
      "kind": "write_create"
    },
    "CreateWhatIfForecast": {
      "operation": "CreateWhatIfForecast",
      "service": "forecast",
      "csp": "aws",
      "independent": false,
      "python_method": "create_what_if_forecast",
      "yaml_action": "create_what_if_forecast",
      "required_params": [
        "WhatIfForecastName",
        "WhatIfAnalysisArn"
      ],
      "optional_params": [
        "TimeSeriesTransformations",
        "TimeSeriesReplacementsDataSource",
        "Tags"
      ],
      "output_fields": {
        "WhatIfForecastArn": {
          "type": "string",
          "description": "<p>The Amazon Resource Name (ARN) of the what-if forecast.</p>",
          "enum": false,
          "operators": [
            "equals",
            "not_equals",
            "contains",
            "in",
            "exists"
          ],
          "compliance_category": "identity"
        }
      },
      "kind": "write_create"
    },
    "CreateWhatIfForecastExport": {
      "operation": "CreateWhatIfForecastExport",
      "service": "forecast",
      "csp": "aws",
      "independent": false,
      "python_method": "create_what_if_forecast_export",
      "yaml_action": "create_what_if_forecast_export",
      "required_params": [
        "WhatIfForecastExportName",
        "WhatIfForecastArns",
        "Destination"
      ],
      "optional_params": [
        "Tags",
        "Format"
      ],
      "output_fields": {
        "WhatIfForecastExportArn": {
          "type": "string",
          "description": "<p>The Amazon Resource Name (ARN) of the what-if forecast.</p>",
          "enum": false,
          "operators": [
            "equals",
            "not_equals",
            "contains",
            "in",
            "exists"
          ],
          "compliance_category": "identity"
        }
      },
      "kind": "write_create"
    },
    "DeleteDataset": {
      "operation": "DeleteDataset",
      "service": "forecast",
      "csp": "aws",
      "independent": false,
      "python_method": "delete_dataset",
      "yaml_action": "delete_dataset",
      "required_params": [
        "DatasetArn"
      ],
      "optional_params": [],
      "output_fields": {},
      "kind": "write_delete"
    },
    "DeleteDatasetGroup": {
      "operation": "DeleteDatasetGroup",
      "service": "forecast",
      "csp": "aws",
      "independent": false,
      "python_method": "delete_dataset_group",
      "yaml_action": "delete_dataset_group",
      "required_params": [
        "DatasetGroupArn"
      ],
      "optional_params": [],
      "output_fields": {},
      "kind": "write_delete"
    },
    "DeleteDatasetImportJob": {
      "operation": "DeleteDatasetImportJob",
      "service": "forecast",
      "csp": "aws",
      "independent": false,
      "python_method": "delete_dataset_import_job",
      "yaml_action": "delete_dataset_import_job",
      "required_params": [
        "DatasetImportJobArn"
      ],
      "optional_params": [],
      "output_fields": {},
      "kind": "write_delete"
    },
    "DeleteExplainability": {
      "operation": "DeleteExplainability",
      "service": "forecast",
      "csp": "aws",
      "independent": false,
      "python_method": "delete_explainability",
      "yaml_action": "delete_explainability",
      "required_params": [
        "ExplainabilityArn"
      ],
      "optional_params": [],
      "output_fields": {},
      "kind": "write_delete"
    },
    "DeleteExplainabilityExport": {
      "operation": "DeleteExplainabilityExport",
      "service": "forecast",
      "csp": "aws",
      "independent": false,
      "python_method": "delete_explainability_export",
      "yaml_action": "delete_explainability_export",
      "required_params": [
        "ExplainabilityExportArn"
      ],
      "optional_params": [],
      "output_fields": {},
      "kind": "write_delete"
    },
    "DeleteForecast": {
      "operation": "DeleteForecast",
      "service": "forecast",
      "csp": "aws",
      "independent": false,
      "python_method": "delete_forecast",
      "yaml_action": "delete_forecast",
      "required_params": [
        "ForecastArn"
      ],
      "optional_params": [],
      "output_fields": {},
      "kind": "write_delete"
    },
    "DeleteForecastExportJob": {
      "operation": "DeleteForecastExportJob",
      "service": "forecast",
      "csp": "aws",
      "independent": false,
      "python_method": "delete_forecast_export_job",
      "yaml_action": "delete_forecast_export_job",
      "required_params": [
        "ForecastExportJobArn"
      ],
      "optional_params": [],
      "output_fields": {},
      "kind": "write_delete"
    },
    "DeleteMonitor": {
      "operation": "DeleteMonitor",
      "service": "forecast",
      "csp": "aws",
      "independent": false,
      "python_method": "delete_monitor",
      "yaml_action": "delete_monitor",
      "required_params": [
        "MonitorArn"
      ],
      "optional_params": [],
      "output_fields": {},
      "kind": "write_delete"
    },
    "DeletePredictor": {
      "operation": "DeletePredictor",
      "service": "forecast",
      "csp": "aws",
      "independent": false,
      "python_method": "delete_predictor",
      "yaml_action": "delete_predictor",
      "required_params": [
        "PredictorArn"
      ],
      "optional_params": [],
      "output_fields": {},
      "kind": "write_delete"
    },
    "DeletePredictorBacktestExportJob": {
      "operation": "DeletePredictorBacktestExportJob",
      "service": "forecast",
      "csp": "aws",
      "independent": false,
      "python_method": "delete_predictor_backtest_export_job",
      "yaml_action": "delete_predictor_backtest_export_job",
      "required_params": [
        "PredictorBacktestExportJobArn"
      ],
      "optional_params": [],
      "output_fields": {},
      "kind": "write_delete"
    },
    "DeleteResourceTree": {
      "operation": "DeleteResourceTree",
      "service": "forecast",
      "csp": "aws",
      "independent": false,
      "python_method": "delete_resource_tree",
      "yaml_action": "delete_resource_tree",
      "required_params": [
        "ResourceArn"
      ],
      "optional_params": [],
      "output_fields": {},
      "kind": "write_delete"
    },
    "DeleteWhatIfAnalysis": {
      "operation": "DeleteWhatIfAnalysis",
      "service": "forecast",
      "csp": "aws",
      "independent": false,
      "python_method": "delete_what_if_analysis",
      "yaml_action": "delete_what_if_analysis",
      "required_params": [
        "WhatIfAnalysisArn"
      ],
      "optional_params": [],
      "output_fields": {},
      "kind": "write_delete"
    },
    "DeleteWhatIfForecast": {
      "operation": "DeleteWhatIfForecast",
      "service": "forecast",
      "csp": "aws",
      "independent": false,
      "python_method": "delete_what_if_forecast",
      "yaml_action": "delete_what_if_forecast",
      "required_params": [
        "WhatIfForecastArn"
      ],
      "optional_params": [],
      "output_fields": {},
      "kind": "write_delete"
    },
    "DeleteWhatIfForecastExport": {
      "operation": "DeleteWhatIfForecastExport",
      "service": "forecast",
      "csp": "aws",
      "independent": false,
      "python_method": "delete_what_if_forecast_export",
      "yaml_action": "delete_what_if_forecast_export",
      "required_params": [
        "WhatIfForecastExportArn"
      ],
      "optional_params": [],
      "output_fields": {},
      "kind": "write_delete"
    },
    "ResumeResource": {
      "operation": "ResumeResource",
      "service": "forecast",
      "csp": "aws",
      "independent": false,
      "python_method": "resume_resource",
      "yaml_action": "resume_resource",
      "required_params": [
        "ResourceArn"
      ],
      "optional_params": [],
      "output_fields": {},
      "kind": "write_other"
    },
    "StopResource": {
      "operation": "StopResource",
      "service": "forecast",
      "csp": "aws",
      "independent": false,
      "python_method": "stop_resource",
      "yaml_action": "stop_resource",
      "required_params": [
        "ResourceArn"
      ],
      "optional_params": [],
      "output_fields": {},
      "kind": "write_other"
    },
    "TagResource": {
      "operation": "TagResource",
      "service": "forecast",
      "csp": "aws",
      "independent": false,
      "python_method": "tag_resource",
      "yaml_action": "tag_resource",
      "required_params": [
        "ResourceArn",
        "Tags"
      ],
      "optional_params": [],
      "output_fields": {},
      "kind": "write_other"
    },
    "UntagResource": {
      "operation": "UntagResource",
      "service": "forecast",
      "csp": "aws",
      "independent": false,
      "python_method": "untag_resource",
      "yaml_action": "untag_resource",
      "required_params": [
        "ResourceArn",
        "TagKeys"
      ],
      "optional_params": [],
      "output_fields": {},
      "kind": "write_other"
    },
    "UpdateDatasetGroup": {
      "operation": "UpdateDatasetGroup",
      "service": "forecast",
      "csp": "aws",
      "independent": false,
      "python_method": "update_dataset_group",
      "yaml_action": "update_dataset_group",
      "required_params": [
        "DatasetGroupArn",
        "DatasetArns"
      ],
      "optional_params": [],
      "output_fields": {},
      "kind": "write_update"
    }
  }
}