{
  "service": "ingress",
  "csp": "k8s",
  "generated_at": "2026-04-16T04:49:56.148170+00:00",
  "total_fields": 4,
  "fields": {
    "k8s.ingress.metadata": {
      "field": "k8s.ingress.metadata",
      "field_short": "metadata",
      "type": "object",
      "description": "",
      "compliance_category": "general",
      "security_impact": null,
      "enum": false,
      "possible_values": null,
      "produced_by": [
        "k8s.ingress.list",
        "k8s.ingress.get"
      ]
    },
    "k8s.ingress.spec": {
      "field": "k8s.ingress.spec",
      "field_short": "spec",
      "type": "object",
      "description": "",
      "compliance_category": "general",
      "security_impact": null,
      "enum": false,
      "possible_values": null,
      "produced_by": [
        "k8s.ingress.list",
        "k8s.ingress.get"
      ]
    },
    "k8s.ingress.spec.rules": {
      "field": "k8s.ingress.spec.rules",
      "field_short": "spec.rules",
      "type": "array",
      "description": "",
      "compliance_category": "network",
      "security_impact": null,
      "enum": false,
      "possible_values": null,
      "produced_by": [
        "k8s.ingress.list",
        "k8s.ingress.get"
      ]
    },
    "k8s.ingress.spec.tls": {
      "field": "k8s.ingress.spec.tls",
      "field_short": "spec.tls",
      "type": "array",
      "description": "",
      "compliance_category": "security",
      "security_impact": "high",
      "enum": false,
      "possible_values": null,
      "produced_by": [
        "k8s.ingress.list",
        "k8s.ingress.get"
      ]
    }
  }
}