{
  "service": "databrew",
  "version": "1.0",
  "kind_rules": {
    "read_list": ["List"],
    "read_get": ["Get", "Describe"],
    "write_create": ["Create", "Start", "Generate", "Import", "Enable", "Register"],
    "write_update": ["Update", "Modify", "Put", "Set", "Change", "Reset", "Patch"],
    "write_delete": ["Delete", "Remove", "Terminate", "Destroy", "Disable", "Detach", "Disassociate", "Untag", "Revoke"],
    "write_apply": ["Apply", "Attach", "Associate", "Add", "Tag", "Authorize", "Unauthorize", "Grant"],
    "other": ["default"]
  },
  "entity_aliases": {
    "databrew.job_run_dataset_name": "databrew.dataset_name",
    "databrew.schedul_resource_arn": "databrew.resource_arn",
    "databrew.project_role_arn": "databrew.role_arn",
    "databrew.recip_resource_arn": "databrew.resource_arn",
    "databrew.profile_job_name": "databrew.job_name",
    "databrew.project_resource_arn": "databrew.resource_arn",
    "databrew.job_dataset_name": "databrew.dataset_name",
    "databrew.recip_project_name": "databrew.project_name",
    "databrew.dataset_resource_arn": "databrew.resource_arn",
    "databrew.job_resource_arn": "databrew.resource_arn",
    "databrew.batch_delete_recipe_version_name": "databrew.recipe_version_name",
    "databrew.ruleset_resource_arn": "databrew.resource_arn",
    "databrew.publish_recipe_name": "databrew.recipe_name",
    "databrew.job_role_arn": "databrew.role_arn",
    "databrew.job_project_name": "databrew.project_name",
    "databrew.project_dataset_name": "databrew.dataset_name",
    "databrew.recipe_job_name": "databrew.job_name",
    "databrew.job_run_run_id": "databrew.run_id",
    "databrew.project_recipe_name": "databrew.recipe_name",
    "databrew.ruleset_target_arn": "databrew.target_arn",
    "databrew.job_run_job_name": "databrew.job_name"
  },
  "overrides": {},
  "operations": {
    "ListDatasets": {
      "kind": "read_list",
      "side_effect": false,
      "sdk": {"client": "databrew", "method": "list_datasets"},
      "consumes": [],
      "produces": [{"entity": "databrew.datasets", "source": "output", "path": "Datasets"}, {"entity": "databrew.next_token", "source": "output", "path": "NextToken"}, {"entity": "databrew.dataset_account_id", "source": "item", "path": "Datasets[].AccountId"}, {"entity": "databrew.dataset_created_by", "source": "item", "path": "Datasets[].CreatedBy"}, {"entity": "databrew.dataset_create_date", "source": "item", "path": "Datasets[].CreateDate"}, {"entity": "databrew.dataset_name", "source": "item", "path": "Datasets[].Name"}, {"entity": "databrew.dataset_format", "source": "item", "path": "Datasets[].Format"}, {"entity": "databrew.dataset_format_options", "source": "item", "path": "Datasets[].FormatOptions"}, {"entity": "databrew.dataset_input", "source": "item", "path": "Datasets[].Input"}, {"entity": "databrew.dataset_last_modified_date", "source": "item", "path": "Datasets[].LastModifiedDate"}, {"entity": "databrew.dataset_last_modified_by", "source": "item", "path": "Datasets[].LastModifiedBy"}, {"entity": "databrew.dataset_source", "source": "item", "path": "Datasets[].Source"}, {"entity": "databrew.dataset_path_options", "source": "item", "path": "Datasets[].PathOptions"}, {"entity": "databrew.dataset_tags", "source": "item", "path": "Datasets[].Tags"}, {"entity": "databrew.resource_arn", "source": "item", "path": "Datasets[].ResourceArn"}],
      "notes": ""
    },
    "ListJobs": {
      "kind": "read_list",
      "side_effect": false,
      "sdk": {"client": "databrew", "method": "list_jobs"},
      "consumes": [],
      "produces": [{"entity": "databrew.jobs", "source": "output", "path": "Jobs"}, {"entity": "databrew.next_token", "source": "output", "path": "NextToken"}, {"entity": "databrew.job_account_id", "source": "item", "path": "Jobs[].AccountId"}, {"entity": "databrew.job_created_by", "source": "item", "path": "Jobs[].CreatedBy"}, {"entity": "databrew.job_create_date", "source": "item", "path": "Jobs[].CreateDate"}, {"entity": "databrew.dataset_name", "source": "item", "path": "Jobs[].DatasetName"}, {"entity": "databrew.job_encryption_key_arn", "source": "item", "path": "Jobs[].EncryptionKeyArn"}, {"entity": "databrew.job_encryption_mode", "source": "item", "path": "Jobs[].EncryptionMode"}, {"entity": "databrew.job_name", "source": "item", "path": "Jobs[].Name"}, {"entity": "databrew.job_type", "source": "item", "path": "Jobs[].Type"}, {"entity": "databrew.job_last_modified_by", "source": "item", "path": "Jobs[].LastModifiedBy"}, {"entity": "databrew.job_last_modified_date", "source": "item", "path": "Jobs[].LastModifiedDate"}, {"entity": "databrew.job_log_subscription", "source": "item", "path": "Jobs[].LogSubscription"}, {"entity": "databrew.job_max_capacity", "source": "item", "path": "Jobs[].MaxCapacity"}, {"entity": "databrew.job_max_retries", "source": "item", "path": "Jobs[].MaxRetries"}, {"entity": "databrew.job_outputs", "source": "item", "path": "Jobs[].Outputs"}, {"entity": "databrew.job_data_catalog_outputs", "source": "item", "path": "Jobs[].DataCatalogOutputs"}, {"entity": "databrew.job_database_outputs", "source": "item", "path": "Jobs[].DatabaseOutputs"}, {"entity": "databrew.project_name", "source": "item", "path": "Jobs[].ProjectName"}, {"entity": "databrew.job_recipe_reference", "source": "item", "path": "Jobs[].RecipeReference"}, {"entity": "databrew.resource_arn", "source": "item", "path": "Jobs[].ResourceArn"}, {"entity": "databrew.role_arn", "source": "item", "path": "Jobs[].RoleArn"}, {"entity": "databrew.job_timeout", "source": "item", "path": "Jobs[].Timeout"}, {"entity": "databrew.job_tags", "source": "item", "path": "Jobs[].Tags"}, {"entity": "databrew.job_sample", "source": "item", "path": "Jobs[].JobSample"}, {"entity": "databrew.job_validation_configurations", "source": "item", "path": "Jobs[].ValidationConfigurations"}],
      "notes": ""
    },
    "ListProjects": {
      "kind": "read_list",
      "side_effect": false,
      "sdk": {"client": "databrew", "method": "list_projects"},
      "consumes": [],
      "produces": [{"entity": "databrew.projects", "source": "output", "path": "Projects"}, {"entity": "databrew.next_token", "source": "output", "path": "NextToken"}, {"entity": "databrew.project_account_id", "source": "item", "path": "Projects[].AccountId"}, {"entity": "databrew.project_create_date", "source": "item", "path": "Projects[].CreateDate"}, {"entity": "databrew.project_created_by", "source": "item", "path": "Projects[].CreatedBy"}, {"entity": "databrew.dataset_name", "source": "item", "path": "Projects[].DatasetName"}, {"entity": "databrew.project_last_modified_date", "source": "item", "path": "Projects[].LastModifiedDate"}, {"entity": "databrew.project_last_modified_by", "source": "item", "path": "Projects[].LastModifiedBy"}, {"entity": "databrew.project_name", "source": "item", "path": "Projects[].Name"}, {"entity": "databrew.recipe_name", "source": "item", "path": "Projects[].RecipeName"}, {"entity": "databrew.resource_arn", "source": "item", "path": "Projects[].ResourceArn"}, {"entity": "databrew.project_sample", "source": "item", "path": "Projects[].Sample"}, {"entity": "databrew.project_tags", "source": "item", "path": "Projects[].Tags"}, {"entity": "databrew.role_arn", "source": "item", "path": "Projects[].RoleArn"}, {"entity": "databrew.project_opened_by", "source": "item", "path": "Projects[].OpenedBy"}, {"entity": "databrew.project_open_date", "source": "item", "path": "Projects[].OpenDate"}],
      "notes": ""
    },
    "ListRecipes": {
      "kind": "read_list",
      "side_effect": false,
      "sdk": {"client": "databrew", "method": "list_recipes"},
      "consumes": [],
      "produces": [{"entity": "databrew.recipes", "source": "output", "path": "Recipes"}, {"entity": "databrew.next_token", "source": "output", "path": "NextToken"}, {"entity": "databrew.recip_created_by", "source": "item", "path": "Recipes[].CreatedBy"}, {"entity": "databrew.recip_create_date", "source": "item", "path": "Recipes[].CreateDate"}, {"entity": "databrew.recip_last_modified_by", "source": "item", "path": "Recipes[].LastModifiedBy"}, {"entity": "databrew.recip_last_modified_date", "source": "item", "path": "Recipes[].LastModifiedDate"}, {"entity": "databrew.project_name", "source": "item", "path": "Recipes[].ProjectName"}, {"entity": "databrew.recip_published_by", "source": "item", "path": "Recipes[].PublishedBy"}, {"entity": "databrew.recip_published_date", "source": "item", "path": "Recipes[].PublishedDate"}, {"entity": "databrew.recip_description", "source": "item", "path": "Recipes[].Description"}, {"entity": "databrew.recip_name", "source": "item", "path": "Recipes[].Name"}, {"entity": "databrew.resource_arn", "source": "item", "path": "Recipes[].ResourceArn"}, {"entity": "databrew.recip_steps", "source": "item", "path": "Recipes[].Steps"}, {"entity": "databrew.recip_tags", "source": "item", "path": "Recipes[].Tags"}, {"entity": "databrew.recip_recipe_version", "source": "item", "path": "Recipes[].RecipeVersion"}],
      "notes": ""
    },
    "ListRulesets": {
      "kind": "read_list",
      "side_effect": false,
      "sdk": {"client": "databrew", "method": "list_rulesets"},
      "consumes": [],
      "produces": [{"entity": "databrew.rulesets", "source": "output", "path": "Rulesets"}, {"entity": "databrew.next_token", "source": "output", "path": "NextToken"}, {"entity": "databrew.ruleset_account_id", "source": "item", "path": "Rulesets[].AccountId"}, {"entity": "databrew.ruleset_created_by", "source": "item", "path": "Rulesets[].CreatedBy"}, {"entity": "databrew.ruleset_create_date", "source": "item", "path": "Rulesets[].CreateDate"}, {"entity": "databrew.ruleset_description", "source": "item", "path": "Rulesets[].Description"}, {"entity": "databrew.ruleset_last_modified_by", "source": "item", "path": "Rulesets[].LastModifiedBy"}, {"entity": "databrew.ruleset_last_modified_date", "source": "item", "path": "Rulesets[].LastModifiedDate"}, {"entity": "databrew.ruleset_name", "source": "item", "path": "Rulesets[].Name"}, {"entity": "databrew.resource_arn", "source": "item", "path": "Rulesets[].ResourceArn"}, {"entity": "databrew.ruleset_rule_count", "source": "item", "path": "Rulesets[].RuleCount"}, {"entity": "databrew.ruleset_tags", "source": "item", "path": "Rulesets[].Tags"}, {"entity": "databrew.target_arn", "source": "item", "path": "Rulesets[].TargetArn"}],
      "notes": ""
    },
    "ListSchedules": {
      "kind": "read_list",
      "side_effect": false,
      "sdk": {"client": "databrew", "method": "list_schedules"},
      "consumes": [],
      "produces": [{"entity": "databrew.schedules", "source": "output", "path": "Schedules"}, {"entity": "databrew.next_token", "source": "output", "path": "NextToken"}, {"entity": "databrew.schedul_account_id", "source": "item", "path": "Schedules[].AccountId"}, {"entity": "databrew.schedul_created_by", "source": "item", "path": "Schedules[].CreatedBy"}, {"entity": "databrew.schedul_create_date", "source": "item", "path": "Schedules[].CreateDate"}, {"entity": "databrew.schedul_job_names", "source": "item", "path": "Schedules[].JobNames"}, {"entity": "databrew.schedul_last_modified_by", "source": "item", "path": "Schedules[].LastModifiedBy"}, {"entity": "databrew.schedul_last_modified_date", "source": "item", "path": "Schedules[].LastModifiedDate"}, {"entity": "databrew.resource_arn", "source": "item", "path": "Schedules[].ResourceArn"}, {"entity": "databrew.schedul_cron_expression", "source": "item", "path": "Schedules[].CronExpression"}, {"entity": "databrew.schedul_tags", "source": "item", "path": "Schedules[].Tags"}, {"entity": "databrew.schedul_name", "source": "item", "path": "Schedules[].Name"}],
      "notes": ""
    },
    "BatchDeleteRecipeVersion": {
      "kind": "other",
      "side_effect": true,
      "sdk": {"client": "databrew", "method": "batch_delete_recipe_version"},
      "consumes": [{"entity": "databrew.error_name", "param": "Name", "required": true, "source": "external"}, {"entity": "databrew.recipe_versions", "param": "RecipeVersions", "required": true, "source": "external"}],
      "produces": [{"entity": "databrew.recipe_version_name", "source": "output", "path": "Name"}, {"entity": "databrew.errors", "source": "output", "path": "Errors"}, {"entity": "databrew.error_code", "source": "item", "path": "Errors.ErrorCode"}, {"entity": "databrew.error_message", "source": "item", "path": "Errors.ErrorMessage"}, {"entity": "databrew.error_recipe_version", "source": "item", "path": "Errors.RecipeVersion"}],
      "notes": ""
    },
    "CreateDataset": {
      "kind": "write_create",
      "side_effect": true,
      "sdk": {"client": "databrew", "method": "create_dataset"},
      "consumes": [{"entity": "databrew.dataset_name", "param": "Name", "required": true, "source": "internal"}, {"entity": "databrew.input", "param": "Input", "required": true, "source": "internal"}],
      "produces": [{"entity": "databrew.dataset_name", "source": "output", "path": "Name"}],
      "notes": ""
    },
    "CreateProfileJob": {
      "kind": "write_create",
      "side_effect": true,
      "sdk": {"client": "databrew", "method": "create_profile_job"},
      "consumes": [{"entity": "databrew.dataset_name", "param": "DatasetName", "required": true, "source": "internal"}, {"entity": "databrew.job_name", "param": "Name", "required": true, "source": "internal"}, {"entity": "databrew.output_location", "param": "OutputLocation", "required": true, "source": "internal"}, {"entity": "databrew.role_arn", "param": "RoleArn", "required": true, "source": "internal"}],
      "produces": [{"entity": "databrew.job_name", "source": "output", "path": "Name"}],
      "notes": ""
    },
    "CreateProject": {
      "kind": "write_create",
      "side_effect": true,
      "sdk": {"client": "databrew", "method": "create_project"},
      "consumes": [{"entity": "databrew.dataset_name", "param": "DatasetName", "required": true, "source": "internal"}, {"entity": "databrew.project_name", "param": "Name", "required": true, "source": "internal"}, {"entity": "databrew.recipe_name", "param": "RecipeName", "required": true, "source": "internal"}, {"entity": "databrew.role_arn", "param": "RoleArn", "required": true, "source": "internal"}],
      "produces": [{"entity": "databrew.project_name", "source": "output", "path": "Name"}],
      "notes": ""
    },
    "CreateRecipe": {
      "kind": "write_create",
      "side_effect": true,
      "sdk": {"client": "databrew", "method": "create_recipe"},
      "consumes": [{"entity": "databrew.recipe_name", "param": "Name", "required": true, "source": "internal"}, {"entity": "databrew.steps", "param": "Steps", "required": true, "source": "internal"}],
      "produces": [{"entity": "databrew.recipe_name", "source": "output", "path": "Name"}],
      "notes": ""
    },
    "CreateRecipeJob": {
      "kind": "write_create",
      "side_effect": true,
      "sdk": {"client": "databrew", "method": "create_recipe_job"},
      "consumes": [{"entity": "databrew.job_name", "param": "Name", "required": true, "source": "internal"}, {"entity": "databrew.role_arn", "param": "RoleArn", "required": true, "source": "internal"}],
      "produces": [{"entity": "databrew.job_name", "source": "output", "path": "Name"}],
      "notes": ""
    },
    "CreateRuleset": {
      "kind": "write_create",
      "side_effect": true,
      "sdk": {"client": "databrew", "method": "create_ruleset"},
      "consumes": [{"entity": "databrew.ruleset_name", "param": "Name", "required": true, "source": "internal"}, {"entity": "databrew.target_arn", "param": "TargetArn", "required": true, "source": "internal"}, {"entity": "databrew.rules", "param": "Rules", "required": true, "source": "internal"}],
      "produces": [{"entity": "databrew.ruleset_name", "source": "output", "path": "Name"}],
      "notes": ""
    },
    "CreateSchedule": {
      "kind": "write_create",
      "side_effect": true,
      "sdk": {"client": "databrew", "method": "create_schedule"},
      "consumes": [{"entity": "databrew.cron_expression", "param": "CronExpression", "required": true, "source": "internal"}, {"entity": "databrew.schedule_name", "param": "Name", "required": true, "source": "internal"}],
      "produces": [{"entity": "databrew.schedule_name", "source": "output", "path": "Name"}],
      "notes": ""
    },
    "DeleteDataset": {
      "kind": "write_delete",
      "side_effect": true,
      "sdk": {"client": "databrew", "method": "delete_dataset"},
      "consumes": [{"entity": "databrew.dataset_name", "param": "Name", "required": true, "source": "internal"}],
      "produces": [{"entity": "databrew.dataset_name", "source": "output", "path": "Name"}],
      "notes": ""
    },
    "DeleteJob": {
      "kind": "write_delete",
      "side_effect": true,
      "sdk": {"client": "databrew", "method": "delete_job"},
      "consumes": [{"entity": "databrew.job_name", "param": "Name", "required": true, "source": "internal"}],
      "produces": [{"entity": "databrew.job_name", "source": "output", "path": "Name"}],
      "notes": ""
    },
    "DeleteProject": {
      "kind": "write_delete",
      "side_effect": true,
      "sdk": {"client": "databrew", "method": "delete_project"},
      "consumes": [{"entity": "databrew.project_name", "param": "Name", "required": true, "source": "internal"}],
      "produces": [{"entity": "databrew.project_name", "source": "output", "path": "Name"}],
      "notes": ""
    },
    "DeleteRecipeVersion": {
      "kind": "write_delete",
      "side_effect": true,
      "sdk": {"client": "databrew", "method": "delete_recipe_version"},
      "consumes": [{"entity": "databrew.recipe_version_name", "param": "Name", "required": true, "source": "internal"}, {"entity": "databrew.recipe_version", "param": "RecipeVersion", "required": true, "source": "internal"}],
      "produces": [{"entity": "databrew.recipe_version_name", "source": "output", "path": "Name"}, {"entity": "databrew.recipe_version", "source": "output", "path": "RecipeVersion"}],
      "notes": ""
    },
    "DeleteRuleset": {
      "kind": "write_delete",
      "side_effect": true,
      "sdk": {"client": "databrew", "method": "delete_ruleset"},
      "consumes": [{"entity": "databrew.ruleset_name", "param": "Name", "required": true, "source": "internal"}],
      "produces": [{"entity": "databrew.ruleset_name", "source": "output", "path": "Name"}],
      "notes": ""
    },
    "DeleteSchedule": {
      "kind": "write_delete",
      "side_effect": true,
      "sdk": {"client": "databrew", "method": "delete_schedule"},
      "consumes": [{"entity": "databrew.schedule_name", "param": "Name", "required": true, "source": "internal"}],
      "produces": [{"entity": "databrew.schedule_name", "source": "output", "path": "Name"}],
      "notes": ""
    },
    "DescribeDataset": {
      "kind": "read_get",
      "side_effect": false,
      "sdk": {"client": "databrew", "method": "describe_dataset"},
      "consumes": [{"entity": "databrew.format_option_name", "param": "Name", "required": true, "source": "external"}],
      "produces": [{"entity": "databrew.created_by", "source": "output", "path": "CreatedBy"}, {"entity": "databrew.create_date", "source": "output", "path": "CreateDate"}, {"entity": "databrew.dataset_name", "source": "output", "path": "Name"}, {"entity": "databrew.format", "source": "output", "path": "Format"}, {"entity": "databrew.format_options", "source": "output", "path": "FormatOptions"}, {"entity": "databrew.input", "source": "output", "path": "Input"}, {"entity": "databrew.last_modified_date", "source": "output", "path": "LastModifiedDate"}, {"entity": "databrew.last_modified_by", "source": "output", "path": "LastModifiedBy"}, {"entity": "databrew.source", "source": "output", "path": "Source"}, {"entity": "databrew.path_options", "source": "output", "path": "PathOptions"}, {"entity": "databrew.tags", "source": "output", "path": "Tags"}, {"entity": "databrew.resource_arn", "source": "output", "path": "ResourceArn"}, {"entity": "databrew.format_option_json", "source": "item", "path": "FormatOptions.Json"}, {"entity": "databrew.format_option_excel", "source": "item", "path": "FormatOptions.Excel"}, {"entity": "databrew.format_option_csv", "source": "item", "path": "FormatOptions.Csv"}],
      "notes": ""
    },
    "DescribeJob": {
      "kind": "read_get",
      "side_effect": false,
      "sdk": {"client": "databrew", "method": "describe_job"},
      "consumes": [{"entity": "databrew.output_name", "param": "Name", "required": true, "source": "external"}],
      "produces": [{"entity": "databrew.create_date", "source": "output", "path": "CreateDate"}, {"entity": "databrew.created_by", "source": "output", "path": "CreatedBy"}, {"entity": "databrew.dataset_name", "source": "output", "path": "DatasetName"}, {"entity": "databrew.encryption_key_arn", "source": "output", "path": "EncryptionKeyArn"}, {"entity": "databrew.encryption_mode", "source": "output", "path": "EncryptionMode"}, {"entity": "databrew.job_name", "source": "output", "path": "Name"}, {"entity": "databrew.type", "source": "output", "path": "Type"}, {"entity": "databrew.last_modified_by", "source": "output", "path": "LastModifiedBy"}, {"entity": "databrew.last_modified_date", "source": "output", "path": "LastModifiedDate"}, {"entity": "databrew.log_subscription", "source": "output", "path": "LogSubscription"}, {"entity": "databrew.max_capacity", "source": "output", "path": "MaxCapacity"}, {"entity": "databrew.max_retries", "source": "output", "path": "MaxRetries"}, {"entity": "databrew.outputs", "source": "output", "path": "Outputs"}, {"entity": "databrew.data_catalog_outputs", "source": "output", "path": "DataCatalogOutputs"}, {"entity": "databrew.database_outputs", "source": "output", "path": "DatabaseOutputs"}, {"entity": "databrew.project_name", "source": "output", "path": "ProjectName"}, {"entity": "databrew.profile_configuration", "source": "output", "path": "ProfileConfiguration"}, {"entity": "databrew.validation_configurations", "source": "output", "path": "ValidationConfigurations"}, {"entity": "databrew.recipe_reference", "source": "output", "path": "RecipeReference"}, {"entity": "databrew.resource_arn", "source": "output", "path": "ResourceArn"}, {"entity": "databrew.role_arn", "source": "output", "path": "RoleArn"}, {"entity": "databrew.tags", "source": "output", "path": "Tags"}, {"entity": "databrew.timeout", "source": "output", "path": "Timeout"}, {"entity": "databrew.job_sample", "source": "output", "path": "JobSample"}, {"entity": "databrew.output_compression_format", "source": "item", "path": "Outputs.CompressionFormat"}, {"entity": "databrew.output_format", "source": "item", "path": "Outputs.Format"}, {"entity": "databrew.output_partition_columns", "source": "item", "path": "Outputs.PartitionColumns"}, {"entity": "databrew.output_location", "source": "item", "path": "Outputs.Location"}, {"entity": "databrew.output_overwrite", "source": "item", "path": "Outputs.Overwrite"}, {"entity": "databrew.output_format_options", "source": "item", "path": "Outputs.FormatOptions"}, {"entity": "databrew.output_max_output_files", "source": "item", "path": "Outputs.MaxOutputFiles"}],
      "notes": ""
    },
    "DescribeJobRun": {
      "kind": "read_get",
      "side_effect": false,
      "sdk": {"client": "databrew", "method": "describe_job_run"},
      "consumes": [{"entity": "databrew.validation_configuration_name", "param": "Name", "required": true, "source": "external"}, {"entity": "databrew.run_id", "param": "RunId", "required": true, "source": "internal"}],
      "produces": [{"entity": "databrew.attempt", "source": "output", "path": "Attempt"}, {"entity": "databrew.completed_on", "source": "output", "path": "CompletedOn"}, {"entity": "databrew.dataset_name", "source": "output", "path": "DatasetName"}, {"entity": "databrew.error_message", "source": "output", "path": "ErrorMessage"}, {"entity": "databrew.execution_time", "source": "output", "path": "ExecutionTime"}, {"entity": "databrew.job_name", "source": "output", "path": "JobName"}, {"entity": "databrew.profile_configuration", "source": "output", "path": "ProfileConfiguration"}, {"entity": "databrew.validation_configurations", "source": "output", "path": "ValidationConfigurations"}, {"entity": "databrew.run_id", "source": "output", "path": "RunId"}, {"entity": "databrew.state", "source": "output", "path": "State"}, {"entity": "databrew.log_subscription", "source": "output", "path": "LogSubscription"}, {"entity": "databrew.log_group_name", "source": "output", "path": "LogGroupName"}, {"entity": "databrew.outputs", "source": "output", "path": "Outputs"}, {"entity": "databrew.data_catalog_outputs", "source": "output", "path": "DataCatalogOutputs"}, {"entity": "databrew.database_outputs", "source": "output", "path": "DatabaseOutputs"}, {"entity": "databrew.recipe_reference", "source": "output", "path": "RecipeReference"}, {"entity": "databrew.started_by", "source": "output", "path": "StartedBy"}, {"entity": "databrew.started_on", "source": "output", "path": "StartedOn"}, {"entity": "databrew.job_sample", "source": "output", "path": "JobSample"}, {"entity": "databrew.validation_configuration_ruleset_arn", "source": "item", "path": "ValidationConfigurations.RulesetArn"}, {"entity": "databrew.validation_configuration_validation_mode", "source": "item", "path": "ValidationConfigurations.ValidationMode"}],
      "notes": ""
    },
    "DescribeProject": {
      "kind": "read_get",
      "side_effect": false,
      "sdk": {"client": "databrew", "method": "describe_project"},
      "consumes": [{"entity": "databrew.sample_name", "param": "Name", "required": true, "source": "external"}],
      "produces": [{"entity": "databrew.create_date", "source": "output", "path": "CreateDate"}, {"entity": "databrew.created_by", "source": "output", "path": "CreatedBy"}, {"entity": "databrew.dataset_name", "source": "output", "path": "DatasetName"}, {"entity": "databrew.last_modified_date", "source": "output", "path": "LastModifiedDate"}, {"entity": "databrew.last_modified_by", "source": "output", "path": "LastModifiedBy"}, {"entity": "databrew.project_name", "source": "output", "path": "Name"}, {"entity": "databrew.recipe_name", "source": "output", "path": "RecipeName"}, {"entity": "databrew.resource_arn", "source": "output", "path": "ResourceArn"}, {"entity": "databrew.sample", "source": "output", "path": "Sample"}, {"entity": "databrew.role_arn", "source": "output", "path": "RoleArn"}, {"entity": "databrew.tags", "source": "output", "path": "Tags"}, {"entity": "databrew.session_status", "source": "output", "path": "SessionStatus"}, {"entity": "databrew.opened_by", "source": "output", "path": "OpenedBy"}, {"entity": "databrew.open_date", "source": "output", "path": "OpenDate"}, {"entity": "databrew.sample_size", "source": "item", "path": "Sample.Size"}, {"entity": "databrew.sample_type", "source": "item", "path": "Sample.Type"}],
      "notes": ""
    },
    "DescribeRecipe": {
      "kind": "read_get",
      "side_effect": false,
      "sdk": {"client": "databrew", "method": "describe_recipe"},
      "consumes": [{"entity": "databrew.step_name", "param": "Name", "required": true, "source": "external"}],
      "produces": [{"entity": "databrew.created_by", "source": "output", "path": "CreatedBy"}, {"entity": "databrew.create_date", "source": "output", "path": "CreateDate"}, {"entity": "databrew.last_modified_by", "source": "output", "path": "LastModifiedBy"}, {"entity": "databrew.last_modified_date", "source": "output", "path": "LastModifiedDate"}, {"entity": "databrew.project_name", "source": "output", "path": "ProjectName"}, {"entity": "databrew.published_by", "source": "output", "path": "PublishedBy"}, {"entity": "databrew.published_date", "source": "output", "path": "PublishedDate"}, {"entity": "databrew.description", "source": "output", "path": "Description"}, {"entity": "databrew.recipe_name", "source": "output", "path": "Name"}, {"entity": "databrew.steps", "source": "output", "path": "Steps"}, {"entity": "databrew.tags", "source": "output", "path": "Tags"}, {"entity": "databrew.resource_arn", "source": "output", "path": "ResourceArn"}, {"entity": "databrew.recipe_version", "source": "output", "path": "RecipeVersion"}, {"entity": "databrew.step_action", "source": "item", "path": "Steps.Action"}, {"entity": "databrew.step_condition_expressions", "source": "item", "path": "Steps.ConditionExpressions"}],
      "notes": ""
    },
    "DescribeRuleset": {
      "kind": "read_get",
      "side_effect": false,
      "sdk": {"client": "databrew", "method": "describe_ruleset"},
      "consumes": [{"entity": "databrew.rul_name", "param": "Name", "required": true, "source": "internal"}],
      "produces": [{"entity": "databrew.ruleset_name", "source": "output", "path": "Name"}, {"entity": "databrew.description", "source": "output", "path": "Description"}, {"entity": "databrew.target_arn", "source": "output", "path": "TargetArn"}, {"entity": "databrew.rules", "source": "output", "path": "Rules"}, {"entity": "databrew.create_date", "source": "output", "path": "CreateDate"}, {"entity": "databrew.created_by", "source": "output", "path": "CreatedBy"}, {"entity": "databrew.last_modified_by", "source": "output", "path": "LastModifiedBy"}, {"entity": "databrew.last_modified_date", "source": "output", "path": "LastModifiedDate"}, {"entity": "databrew.resource_arn", "source": "output", "path": "ResourceArn"}, {"entity": "databrew.tags", "source": "output", "path": "Tags"}, {"entity": "databrew.rul_name", "source": "item", "path": "Rules.Name"}, {"entity": "databrew.rul_disabled", "source": "item", "path": "Rules.Disabled"}, {"entity": "databrew.rul_check_expression", "source": "item", "path": "Rules.CheckExpression"}, {"entity": "databrew.rul_substitution_map", "source": "item", "path": "Rules.SubstitutionMap"}, {"entity": "databrew.rul_threshold", "source": "item", "path": "Rules.Threshold"}, {"entity": "databrew.rul_column_selectors", "source": "item", "path": "Rules.ColumnSelectors"}],
      "notes": ""
    },
    "DescribeSchedule": {
      "kind": "read_get",
      "side_effect": false,
      "sdk": {"client": "databrew", "method": "describe_schedule"},
      "consumes": [{"entity": "databrew.job_nam_name", "param": "Name", "required": true, "source": "external"}],
      "produces": [{"entity": "databrew.create_date", "source": "output", "path": "CreateDate"}, {"entity": "databrew.created_by", "source": "output", "path": "CreatedBy"}, {"entity": "databrew.job_names", "source": "output", "path": "JobNames"}, {"entity": "databrew.last_modified_by", "source": "output", "path": "LastModifiedBy"}, {"entity": "databrew.last_modified_date", "source": "output", "path": "LastModifiedDate"}, {"entity": "databrew.resource_arn", "source": "output", "path": "ResourceArn"}, {"entity": "databrew.cron_expression", "source": "output", "path": "CronExpression"}, {"entity": "databrew.tags", "source": "output", "path": "Tags"}, {"entity": "databrew.schedule_name", "source": "output", "path": "Name"}],
      "notes": ""
    },
    "ListJobRuns": {
      "kind": "read_list",
      "side_effect": false,
      "sdk": {"client": "databrew", "method": "list_job_runs"},
      "consumes": [{"entity": "databrew.job_run_name", "param": "Name", "required": true, "source": "external"}],
      "produces": [{"entity": "databrew.job_runs", "source": "output", "path": "JobRuns"}, {"entity": "databrew.next_token", "source": "output", "path": "NextToken"}, {"entity": "databrew.job_run_attempt", "source": "item", "path": "JobRuns[].Attempt"}, {"entity": "databrew.job_run_completed_on", "source": "item", "path": "JobRuns[].CompletedOn"}, {"entity": "databrew.dataset_name", "source": "item", "path": "JobRuns[].DatasetName"}, {"entity": "databrew.job_run_error_message", "source": "item", "path": "JobRuns[].ErrorMessage"}, {"entity": "databrew.job_run_execution_time", "source": "item", "path": "JobRuns[].ExecutionTime"}, {"entity": "databrew.job_name", "source": "item", "path": "JobRuns[].JobName"}, {"entity": "databrew.run_id", "source": "item", "path": "JobRuns[].RunId"}, {"entity": "databrew.job_run_state", "source": "item", "path": "JobRuns[].State"}, {"entity": "databrew.job_run_log_subscription", "source": "item", "path": "JobRuns[].LogSubscription"}, {"entity": "databrew.job_run_log_group_name", "source": "item", "path": "JobRuns[].LogGroupName"}, {"entity": "databrew.job_run_outputs", "source": "item", "path": "JobRuns[].Outputs"}, {"entity": "databrew.job_run_data_catalog_outputs", "source": "item", "path": "JobRuns[].DataCatalogOutputs"}, {"entity": "databrew.job_run_database_outputs", "source": "item", "path": "JobRuns[].DatabaseOutputs"}, {"entity": "databrew.job_run_recipe_reference", "source": "item", "path": "JobRuns[].RecipeReference"}, {"entity": "databrew.job_run_started_by", "source": "item", "path": "JobRuns[].StartedBy"}, {"entity": "databrew.job_run_started_on", "source": "item", "path": "JobRuns[].StartedOn"}, {"entity": "databrew.job_run_job_sample", "source": "item", "path": "JobRuns[].JobSample"}, {"entity": "databrew.job_run_validation_configurations", "source": "item", "path": "JobRuns[].ValidationConfigurations"}],
      "notes": ""
    },
    "ListRecipeVersions": {
      "kind": "read_list",
      "side_effect": false,
      "sdk": {"client": "databrew", "method": "list_recipe_versions"},
      "consumes": [{"entity": "databrew.recip_name", "param": "Name", "required": true, "source": "internal"}],
      "produces": [{"entity": "databrew.next_token", "source": "output", "path": "NextToken"}, {"entity": "databrew.recipes", "source": "output", "path": "Recipes"}, {"entity": "databrew.recip_created_by", "source": "item", "path": "Recipes[].CreatedBy"}, {"entity": "databrew.recip_create_date", "source": "item", "path": "Recipes[].CreateDate"}, {"entity": "databrew.recip_last_modified_by", "source": "item", "path": "Recipes[].LastModifiedBy"}, {"entity": "databrew.recip_last_modified_date", "source": "item", "path": "Recipes[].LastModifiedDate"}, {"entity": "databrew.project_name", "source": "item", "path": "Recipes[].ProjectName"}, {"entity": "databrew.recip_published_by", "source": "item", "path": "Recipes[].PublishedBy"}, {"entity": "databrew.recip_published_date", "source": "item", "path": "Recipes[].PublishedDate"}, {"entity": "databrew.recip_description", "source": "item", "path": "Recipes[].Description"}, {"entity": "databrew.recip_name", "source": "item", "path": "Recipes[].Name"}, {"entity": "databrew.resource_arn", "source": "item", "path": "Recipes[].ResourceArn"}, {"entity": "databrew.recip_steps", "source": "item", "path": "Recipes[].Steps"}, {"entity": "databrew.recip_tags", "source": "item", "path": "Recipes[].Tags"}, {"entity": "databrew.recip_recipe_version", "source": "item", "path": "Recipes[].RecipeVersion"}],
      "notes": ""
    },
    "ListTagsForResource": {
      "kind": "read_list",
      "side_effect": false,
      "sdk": {"client": "databrew", "method": "list_tags_for_resource"},
      "consumes": [{"entity": "databrew.resource_arn", "param": "ResourceArn", "required": true, "source": "internal"}],
      "produces": [{"entity": "databrew.tags", "source": "output", "path": "Tags"}],
      "notes": ""
    },
    "PublishRecipe": {
      "kind": "other",
      "side_effect": true,
      "sdk": {"client": "databrew", "method": "publish_recipe"},
      "consumes": [{"entity": "databrew.recipe_name", "param": "Name", "required": true, "source": "internal"}],
      "produces": [{"entity": "databrew.recipe_name", "source": "output", "path": "Name"}],
      "notes": ""
    },
    "SendProjectSessionAction": {
      "kind": "other",
      "side_effect": true,
      "sdk": {"client": "databrew", "method": "send_project_session_action"},
      "consumes": [{"entity": "databrew.send_project_session_action_name", "param": "Name", "required": true, "source": "internal"}],
      "produces": [{"entity": "databrew.result", "source": "output", "path": "Result"}, {"entity": "databrew.send_project_session_action_name", "source": "output", "path": "Name"}, {"entity": "databrew.action_id", "source": "output", "path": "ActionId"}],
      "notes": ""
    },
    "StartJobRun": {
      "kind": "write_create",
      "side_effect": true,
      "sdk": {"client": "databrew", "method": "start_job_run"},
      "consumes": [{"entity": "databrew.run_id_name", "param": "Name", "required": true, "source": "external"}],
      "produces": [{"entity": "databrew.run_id", "source": "output", "path": "RunId"}],
      "notes": ""
    },
    "StartProjectSession": {
      "kind": "write_create",
      "side_effect": true,
      "sdk": {"client": "databrew", "method": "start_project_session"},
      "consumes": [{"entity": "databrew.project_session_name", "param": "Name", "required": true, "source": "internal"}],
      "produces": [{"entity": "databrew.project_session_name", "source": "output", "path": "Name"}, {"entity": "databrew.client_session_id", "source": "output", "path": "ClientSessionId"}],
      "notes": ""
    },
    "StopJobRun": {
      "kind": "other",
      "side_effect": true,
      "sdk": {"client": "databrew", "method": "stop_job_run"},
      "consumes": [{"entity": "databrew.run_id_name", "param": "Name", "required": true, "source": "external"}, {"entity": "databrew.run_id", "param": "RunId", "required": true, "source": "internal"}],
      "produces": [{"entity": "databrew.run_id", "source": "output", "path": "RunId"}],
      "notes": ""
    },
    "TagResource": {
      "kind": "write_apply",
      "side_effect": true,
      "sdk": {"client": "databrew", "method": "tag_resource"},
      "consumes": [{"entity": "databrew.resource_arn", "param": "ResourceArn", "required": true, "source": "internal"}, {"entity": "databrew.tags", "param": "Tags", "required": true, "source": "internal"}],
      "produces": [],
      "notes": ""
    },
    "UntagResource": {
      "kind": "write_delete",
      "side_effect": true,
      "sdk": {"client": "databrew", "method": "untag_resource"},
      "consumes": [{"entity": "databrew.resource_arn", "param": "ResourceArn", "required": true, "source": "internal"}, {"entity": "databrew.tag_keys", "param": "TagKeys", "required": true, "source": "external"}],
      "produces": [],
      "notes": ""
    },
    "UpdateDataset": {
      "kind": "write_update",
      "side_effect": true,
      "sdk": {"client": "databrew", "method": "update_dataset"},
      "consumes": [{"entity": "databrew.dataset_name", "param": "Name", "required": true, "source": "internal"}, {"entity": "databrew.input", "param": "Input", "required": true, "source": "internal"}],
      "produces": [{"entity": "databrew.dataset_name", "source": "output", "path": "Name"}],
      "notes": ""
    },
    "UpdateProfileJob": {
      "kind": "write_update",
      "side_effect": true,
      "sdk": {"client": "databrew", "method": "update_profile_job"},
      "consumes": [{"entity": "databrew.job_name", "param": "Name", "required": true, "source": "internal"}, {"entity": "databrew.output_location", "param": "OutputLocation", "required": true, "source": "internal"}, {"entity": "databrew.role_arn", "param": "RoleArn", "required": true, "source": "internal"}],
      "produces": [{"entity": "databrew.job_name", "source": "output", "path": "Name"}],
      "notes": ""
    },
    "UpdateProject": {
      "kind": "write_update",
      "side_effect": true,
      "sdk": {"client": "databrew", "method": "update_project"},
      "consumes": [{"entity": "databrew.role_arn", "param": "RoleArn", "required": true, "source": "internal"}, {"entity": "databrew.last_modified_date_name", "param": "Name", "required": true, "source": "external"}],
      "produces": [{"entity": "databrew.last_modified_date", "source": "output", "path": "LastModifiedDate"}, {"entity": "databrew.project_name", "source": "output", "path": "Name"}],
      "notes": ""
    },
    "UpdateRecipe": {
      "kind": "write_update",
      "side_effect": true,
      "sdk": {"client": "databrew", "method": "update_recipe"},
      "consumes": [{"entity": "databrew.recipe_name", "param": "Name", "required": true, "source": "internal"}],
      "produces": [{"entity": "databrew.recipe_name", "source": "output", "path": "Name"}],
      "notes": ""
    },
    "UpdateRecipeJob": {
      "kind": "write_update",
      "side_effect": true,
      "sdk": {"client": "databrew", "method": "update_recipe_job"},
      "consumes": [{"entity": "databrew.job_name", "param": "Name", "required": true, "source": "internal"}, {"entity": "databrew.role_arn", "param": "RoleArn", "required": true, "source": "internal"}],
      "produces": [{"entity": "databrew.job_name", "source": "output", "path": "Name"}],
      "notes": ""
    },
    "UpdateRuleset": {
      "kind": "write_update",
      "side_effect": true,
      "sdk": {"client": "databrew", "method": "update_ruleset"},
      "consumes": [{"entity": "databrew.ruleset_name", "param": "Name", "required": true, "source": "internal"}, {"entity": "databrew.rules", "param": "Rules", "required": true, "source": "internal"}],
      "produces": [{"entity": "databrew.ruleset_name", "source": "output", "path": "Name"}],
      "notes": ""
    },
    "UpdateSchedule": {
      "kind": "write_update",
      "side_effect": true,
      "sdk": {"client": "databrew", "method": "update_schedule"},
      "consumes": [{"entity": "databrew.cron_expression", "param": "CronExpression", "required": true, "source": "internal"}, {"entity": "databrew.schedule_name", "param": "Name", "required": true, "source": "internal"}],
      "produces": [{"entity": "databrew.schedule_name", "source": "output", "path": "Name"}],
      "notes": ""
    }
  }
}