{
  "service": "playwrighttesting",
  "csp": "azure",
  "data_quality": "enriched",
  "read_only": true,
  "roots": [
    {
      "op": "list_by_account",
      "produces": [
        "playwrighttesting.value",
        "playwrighttesting.properties"
      ]
    },
    {
      "op": "list_by_resource_group",
      "produces": [
        "playwrighttesting.value",
        "playwrighttesting.properties"
      ]
    },
    {
      "op": "list_by_subscription",
      "produces": [
        "playwrighttesting.value",
        "playwrighttesting.properties"
      ]
    },
    {
      "op": "list",
      "produces": [
        "playwrighttesting.value",
        "playwrighttesting.name",
        "playwrighttesting.is_data_action",
        "playwrighttesting.display",
        "playwrighttesting.origin",
        "playwrighttesting.action_type"
      ]
    },
    {
      "op": "list_by_subscription",
      "produces": [
        "playwrighttesting.value",
        "playwrighttesting.properties"
      ]
    },
    {
      "op": "list_by_account",
      "produces": [
        "playwrighttesting.value",
        "playwrighttesting.properties"
      ]
    },
    {
      "op": "list_by_resource_group",
      "produces": [
        "playwrighttesting.value",
        "playwrighttesting.properties"
      ]
    },
    {
      "op": "list_by_subscription",
      "produces": [
        "playwrighttesting.value",
        "playwrighttesting.properties"
      ]
    },
    {
      "op": "list",
      "produces": [
        "playwrighttesting.value",
        "playwrighttesting.name",
        "playwrighttesting.is_data_action",
        "playwrighttesting.display",
        "playwrighttesting.origin",
        "playwrighttesting.action_type"
      ]
    },
    {
      "op": "list_by_subscription",
      "produces": [
        "playwrighttesting.value",
        "playwrighttesting.properties"
      ]
    },
    {
      "op": "list_by_account",
      "produces": [
        "playwrighttesting.value",
        "playwrighttesting.properties"
      ]
    },
    {
      "op": "list_by_resource_group",
      "produces": [
        "playwrighttesting.value",
        "playwrighttesting.properties"
      ]
    },
    {
      "op": "list_by_subscription",
      "produces": [
        "playwrighttesting.value",
        "playwrighttesting.properties"
      ]
    },
    {
      "op": "list",
      "produces": [
        "playwrighttesting.value",
        "playwrighttesting.name",
        "playwrighttesting.is_data_action",
        "playwrighttesting.display",
        "playwrighttesting.origin",
        "playwrighttesting.action_type"
      ]
    },
    {
      "op": "list_by_subscription",
      "produces": [
        "playwrighttesting.value",
        "playwrighttesting.properties"
      ]
    }
  ],
  "entity_paths": {
    "playwrighttesting.value": [
      {
        "operations": [
          "list_by_subscription"
        ],
        "produces": {
          "list_by_subscription": [
            "playwrighttesting.value"
          ]
        },
        "consumes": {
          "list_by_subscription": []
        },
        "external_inputs": []
      }
    ],
    "playwrighttesting.properties": [
      {
        "operations": [
          "list_by_subscription"
        ],
        "produces": {
          "list_by_subscription": [
            "playwrighttesting.properties"
          ]
        },
        "consumes": {
          "list_by_subscription": []
        },
        "external_inputs": []
      }
    ],
    "playwrighttesting.name": [
      {
        "operations": [
          "list"
        ],
        "produces": {
          "list": [
            "playwrighttesting.name"
          ]
        },
        "consumes": {
          "list": []
        },
        "external_inputs": []
      }
    ],
    "playwrighttesting.is_data_action": [
      {
        "operations": [
          "list"
        ],
        "produces": {
          "list": [
            "playwrighttesting.is_data_action"
          ]
        },
        "consumes": {
          "list": []
        },
        "external_inputs": []
      }
    ],
    "playwrighttesting.display": [
      {
        "operations": [
          "list"
        ],
        "produces": {
          "list": [
            "playwrighttesting.display"
          ]
        },
        "consumes": {
          "list": []
        },
        "external_inputs": []
      }
    ],
    "playwrighttesting.origin": [
      {
        "operations": [
          "list"
        ],
        "produces": {
          "list": [
            "playwrighttesting.origin"
          ]
        },
        "consumes": {
          "list": []
        },
        "external_inputs": []
      }
    ],
    "playwrighttesting.action_type": [
      {
        "operations": [
          "list"
        ],
        "produces": {
          "list": [
            "playwrighttesting.action_type"
          ]
        },
        "consumes": {
          "list": []
        },
        "external_inputs": []
      }
    ]
  }
}