{
  "service": "ai_anomaly_detection",
  "csp": "oci",
  "generated_at": "2026-04-16T00:00:00Z",
  "operations": {
    "list_ai_private_endpoints": {
      "operation": "list_ai_private_endpoints",
      "service": "ai_anomaly_detection",
      "csp": "oci",
      "kind": "read_list",
      "independent": true,
      "python_method": "list_ai_private_endpoints",
      "yaml_action": "list_ai_private_endpoints",
      "required_params": ["compartmentId"],
      "optional_params": [],
      "output_fields": ["ocid", "compartment_id", "name", "status", "time_created", "freeform_tags", "defined_tags"]
    },
    "list_data_assets": {
      "operation": "list_data_assets",
      "service": "ai_anomaly_detection",
      "csp": "oci",
      "kind": "read_list",
      "independent": true,
      "python_method": "list_data_assets",
      "yaml_action": "list_data_assets",
      "required_params": ["compartmentId"],
      "optional_params": [],
      "output_fields": ["ocid", "compartment_id", "name", "status", "time_created", "freeform_tags", "defined_tags"]
    },
    "list_detectors": {
      "operation": "list_detectors",
      "service": "ai_anomaly_detection",
      "csp": "oci",
      "kind": "read_list",
      "independent": true,
      "python_method": "list_detectors",
      "yaml_action": "list_detectors",
      "required_params": ["compartmentId"],
      "optional_params": [],
      "output_fields": ["ocid", "compartment_id", "name", "status", "time_created", "freeform_tags", "defined_tags"]
    },
    "list_models": {
      "operation": "list_models",
      "service": "ai_anomaly_detection",
      "csp": "oci",
      "kind": "read_list",
      "independent": true,
      "python_method": "list_models",
      "yaml_action": "list_models",
      "required_params": ["compartmentId"],
      "optional_params": [],
      "output_fields": ["ocid", "compartment_id", "name", "status", "time_created", "freeform_tags", "defined_tags"]
    },
    "list_projects": {
      "operation": "list_projects",
      "service": "ai_anomaly_detection",
      "csp": "oci",
      "kind": "read_list",
      "independent": true,
      "python_method": "list_projects",
      "yaml_action": "list_projects",
      "required_params": ["compartmentId"],
      "optional_params": [],
      "output_fields": ["ocid", "compartment_id", "name", "status", "time_created", "freeform_tags", "defined_tags"]
    },
    "get_detector": {
      "operation": "get_detector",
      "service": "ai_anomaly_detection",
      "csp": "oci",
      "kind": "read_get",
      "independent": false,
      "python_method": "get_detector",
      "yaml_action": "get_detector",
      "required_params": ["DetectorId"],
      "optional_params": [],
      "output_fields": ["ocid", "compartment_id", "name", "status", "time_created", "freeform_tags", "defined_tags"]
    }
  }
}
