{
  "service": "authorization",
  "generated_at": "2026-01-21T22:22:55.562760",
  "total_fields": 0,
  "root_operations_available": [
    "permissions.list_for_resource_group",
    "permissions.list_for_resource",
    "providermetadata.list",
    "roleassignments.list",
    "roleassignments.list_for_resource_group",
    "roleassignments.list_for_resource",
    "root.list_for_resource_group",
    "root.list",
    "root.list_for_resource"
  ],
  "minimal_operations": {
    "selected_operations": [
      {
        "operation": "roleassignments.list",
        "type": "INDEPENDENT",
        "entities_covered": [
          "authorization.next_link",
          "authorization.role__id",
          "authorization.role_assignment__name",
          "authorization.scope",
          "authorization.value",
          "authorization.value_can_delegate",
          "authorization.value_principal_id",
          "authorization.value_role_definition_id",
          "authorization.value_type"
        ],
        "dependencies": [],
        "arns_produced": [],
        "arn_count": 0,
        "primary_arn_count": 0,
        "priority": "INDEPENDENT",
        "dependencies_logic": "NONE",
        "dependencies_required": "NONE",
        "dependencies_count": 0,
        "dependencies_note": "No dependencies - can be called independently"
      },
      {
        "operation": "providermetadata.list",
        "type": "INDEPENDENT",
        "entities_covered": [
          "authorization.providermetadata_id",
          "authorization.providermetadata_name",
          "authorization.value_operations",
          "authorization.value_resource_types"
        ],
        "dependencies": [],
        "arns_produced": [],
        "arn_count": 0,
        "primary_arn_count": 0,
        "priority": "INDEPENDENT",
        "dependencies_logic": "NONE",
        "dependencies_required": "NONE",
        "dependencies_count": 0,
        "dependencies_note": "No dependencies - can be called independently"
      },
      {
        "operation": "root.list_for_resource",
        "type": "INDEPENDENT",
        "entities_covered": [
          "authorization.value_actions",
          "authorization.value_data_actions",
          "authorization.value_not_actions",
          "authorization.value_not_data_actions"
        ],
        "dependencies": [],
        "arns_produced": [],
        "arn_count": 0,
        "primary_arn_count": 0,
        "priority": "INDEPENDENT",
        "dependencies_logic": "NONE",
        "dependencies_required": "NONE",
        "dependencies_count": 0,
        "dependencies_note": "No dependencies - can be called independently"
      }
    ],
    "total_entities_needed": 17,
    "entities_covered": 17,
    "entities_remaining": 0,
    "coverage_percentage": 100.0
  },
  "arn_summary": {
    "total_arns_produced": 0,
    "primary_resource_arns": 0,
    "other_arns": 0,
    "total_unique_arns": 0,
    "deduplicated": true
  },
  "arn_deduplication": {},
  "summary": {
    "total_operations_needed": 3,
    "independent_operations": 3,
    "dependent_operations": 0,
    "coverage_percentage": 100.0
  }
}